pymodins/__init__.py
pymodins/__main__.py
pymodins/installer.py
pymodins/linux.py
pymodins/testing.py
pymodins/ui.py
pymodins-3.2.dist-info/LICENSE
pymodins-3.2.dist-info/METADATA
pymodins-3.2.dist-info/WHEEL
pymodins-3.2.dist-info/entry_points.txt
pymodins-3.2.dist-info/top_level.txt
pymodins-3.2.dist-info/RECORD
