Metadata-Version: 2.1
Name: pymodins
Version: 3.2
Summary: A Python module installer for newcomers and seasoned developers.
Home-page: https://github.com/Nandhan-KA/pymodins
Author: Nandhan K
Author-email: developer.nandhank@gmail.com
Keywords: Python Module Installer,Python Package Installer,pymodins,Nandhan K
Platform: win32
Platform: linux
Classifier: Programming Language :: Python :: 3
Classifier: License :: OSI Approved :: MIT License
Classifier: Operating System :: Microsoft :: Windows
Classifier: Operating System :: POSIX :: Linux
Classifier: Environment :: Win32 (MS Windows)
Classifier: Programming Language :: Python
Classifier: Programming Language :: Python :: 3.6
Classifier: Programming Language :: Python :: 3.7
Classifier: Programming Language :: Python :: 3.8
Classifier: Programming Language :: Python :: 3.9
Classifier: Programming Language :: Python :: 3.10
Classifier: Programming Language :: Python :: 3.11
Classifier: Programming Language :: Python :: 3.12
Requires-Python: >=3.6
License-File: LICENSE
Requires-Dist: rich
